drheader/__init__.py
drheader/core.py
drheader/report.py
drheader/utils.py
drheader/cli/__init__.py
drheader/cli/cli.py
drheader/cli/utils.py
drheader/resources/delimiters.json
drheader/resources/rules.yml
drheader/resources/cli/bulk_compare_schema.json
drheader/resources/cli/bulk_scan_schema.json
drheader/validators/__init__.py
drheader/validators/base.py
drheader/validators/cookie_validator.py
drheader/validators/directive_validator.py
drheader/validators/header_validator.py
drheader-2.0.0.dist-info/LICENSE
drheader-2.0.0.dist-info/METADATA
drheader-2.0.0.dist-info/WHEEL
drheader-2.0.0.dist-info/entry_points.txt
drheader-2.0.0.dist-info/top_level.txt
drheader-2.0.0.dist-info/RECORD
