Metadata-Version: 2.1
Name: drheader
Version: 2.0.0
Summary: DrHEADer helps with the audit of security headers received in response to a single request or a list of requests.
Home-page: https://github.com/santandersecurityresearch/drheader
Author: Santander UK Security Engineering
Keywords: drheader
Classifier: Development Status :: 5 - Production/Stable
Classifier: Environment :: Console
Classifier: Intended Audience :: Developers
Classifier: Natural Language :: English
Classifier: Programming Language :: Python :: 3.8
Classifier: Programming Language :: Python :: 3.9
Classifier: Programming Language :: Python :: 3.10
Classifier: Programming Language :: Python :: 3.11
Classifier: Topic :: Security
License-File: LICENSE
Requires-Dist: requests >=2.22.0
Requires-Dist: jsonschema ==4.19.2
Requires-Dist: Click >=7.0
Requires-Dist: tabulate ==0.9.0
Requires-Dist: pyyaml ==6.0.1
Requires-Dist: junit-xml ==1.9
